covid19_inference/__init__.py
covid19_inference/_dev_helper.py
covid19_inference/_version.py
covid19_inference/sampling.py
covid19_inference/data_retrieval/_Financial_Times.py
covid19_inference/data_retrieval/_Google.py
covid19_inference/data_retrieval/_JHU.py
covid19_inference/data_retrieval/_OWD.py
covid19_inference/data_retrieval/_OxCGRT.py
covid19_inference/data_retrieval/_RKI.py
covid19_inference/data_retrieval/_RKI_situation_reports.py
covid19_inference/data_retrieval/__init__.py
covid19_inference/data_retrieval/retrieval.py
covid19_inference/data_retrieval/countries/__init__.py
covid19_inference/data_retrieval/countries/_belgium_epistat_wiv_isp.py
covid19_inference/data_retrieval/countries/_czechia_onemoceni.py
covid19_inference/data_retrieval/countries/_france_data_gouv_fr.py
covid19_inference/data_retrieval/countries/_france_opencovid_fr.py
covid19_inference/data_retrieval/countries/_ireland_data_gov_ie.py
covid19_inference/data_retrieval/countries/_latvia_data_gov_lv.py
covid19_inference/data_retrieval/countries/_netherlands_data_rvim_nl.py
covid19_inference/data_retrieval/countries/_portugal_dgs.py
covid19_inference/data_retrieval/countries/_switzerland.py
covid19_inference/model/__init__.py
covid19_inference/model/delay.py
covid19_inference/model/likelihood.py
covid19_inference/model/model.py
covid19_inference/model/utility.py
covid19_inference/model/week_modulation.py
covid19_inference/model/compartmental_models/SEIR.py
covid19_inference/model/compartmental_models/SIR.py
covid19_inference/model/compartmental_models/__init__.py
covid19_inference/model/compartmental_models/kernelized_spread.py
covid19_inference/model/compartmental_models/legacy.py
covid19_inference/model/compartmental_models/uncorrelated_priors.py
covid19_inference/model/spreading_rate/__init__.py
covid19_inference/model/spreading_rate/change_points.py
covid19_inference/model/spreading_rate/lambda_t_with_linear_interp.py
covid19_inference/model/spreading_rate/lambda_t_with_sigmoids.py
covid19_inference-0.5.0.dist-info/LICENSE
covid19_inference-0.5.0.dist-info/METADATA
covid19_inference-0.5.0.dist-info/WHEEL
covid19_inference-0.5.0.dist-info/top_level.txt
covid19_inference-0.5.0.dist-info/RECORD
