Metadata-Version: 2.1
Name: covid19-inference
Version: 0.5.0
Summary: Toolbox for inference and forecast of the spread of the Coronavirus.
Home-page: https://github.com/Priesemann-Group/covid19_inference
Author: Jonas Dehning, Johannes Zierenberg, F. Paul Spitzner, Michael Wibral, Joao Pinheiro Neto, Michael Wilczek, Sebastian B. Mohr, Viola Priesemann
Author-email: jonas.dehning@ds.mpg.de
Requires-Python: >=3.6.0
License-File: LICENSE
Requires-Dist: numpy
Requires-Dist: matplotlib
Requires-Dist: pymc (>=5.0.0)
Requires-Dist: pytensor
Requires-Dist: pandas
Requires-Dist: pytest
Requires-Dist: requests
Requires-Dist: numpyro
Requires-Dist: cairosvg
Requires-Dist: watermark
